holdem_calc/__init__.py
holdem_calc/holdem_argparser.py
holdem_calc/holdem_calc.py
holdem_calc/holdem_functions.py
holdem_calc/parallel_holdem_calc.py
holdem_calc-1.0.0.dist-info/LICENSE
holdem_calc-1.0.0.dist-info/METADATA
holdem_calc-1.0.0.dist-info/WHEEL
holdem_calc-1.0.0.dist-info/top_level.txt
holdem_calc-1.0.0.dist-info/RECORD
