Metadata-Version: 2.1
Name: holdem_calc
Version: 1.0.0
Summary: Holdem Calculator library
Home-page: https://github.com/RoelandMatthijssens/holdem_calc
Author: Enermis
Author-email: roeland.matthijssens@gmail.com
License: MIT
Platform: UNKNOWN
Requires-Python: >=3.6
